cuuats.datamodel-0.2.0-py2.7-nspkg.pth
cuuats/datamodel/__init__.py
cuuats/datamodel/domains.py
cuuats/datamodel/exceptions.py
cuuats/datamodel/factory.py
cuuats/datamodel/features.py
cuuats/datamodel/field_values.py
cuuats/datamodel/fields.py
cuuats/datamodel/manytomany.py
cuuats/datamodel/query.py
cuuats/datamodel/scales.py
cuuats/datamodel/tests.py
cuuats/datamodel/utils.py
cuuats/datamodel/workspaces.py
cuuats.datamodel-0.2.0.dist-info/LICENSE.txt
cuuats.datamodel-0.2.0.dist-info/METADATA
cuuats.datamodel-0.2.0.dist-info/RECORD
cuuats.datamodel-0.2.0.dist-info/WHEEL
cuuats.datamodel-0.2.0.dist-info/namespace_packages.txt
cuuats.datamodel-0.2.0.dist-info/top_level.txt
