Metadata-Version: 2.1
Name: cuuats.datamodel
Version: 0.2.0
Summary: A lightweight data access layer for ArcGIS
Home-page: https://cuuats.org/
Author: Matt Yoder
Author-email: myoder@ccrpc.org
License: UNKNOWN
Download-URL: https://github.com/CUUATS/cuuats.datamodel/tarball/0.2.0
Keywords: ArcGIS GIS data geodatabase
Platform: UNKNOWN
Classifier: Development Status :: 3 - Alpha
Classifier: Environment :: Win32 (MS Windows)
Classifier: Intended Audience :: Developers
Classifier: License :: OSI Approved :: BSD License
Classifier: Topic :: Database
Classifier: Topic :: Scientific/Engineering :: GIS
Classifier: Programming Language :: Python :: 2.7
